apb/apb.v
module apb(

input pclk,
input presetn,
input psel,
input penable,
input pwrite,
input [31:0] pwdata,
output reg [31:0] prdata,
output reg pready,
input [31:0] paddr

);

reg [31:0] memory [0:31] ;
reg [1:0] state;

reg [1:0] next_state;

    localparam IDLE  = 2'b00;
    localparam SETUP = 2'b01;
    localparam ACCESS  = 2'b10;

integer i;
initial begin
    for (i = 0; i < 32; i = i + 1) begin
        memory[i] = 32'd0;
    end
    memory[4]=32'd4;
end

always @(*) begin
next_state = state;
    prdata = 32'd0;
    pready = 1'b0;
case(state)

IDLE: begin
  
    if(psel) begin
      next_state=SETUP;
    end

end
SETUP: begin
if (psel) begin
                    next_state = ACCESS; 
                end else begin
                    next_state = IDLE;
                end
end

ACCESS: begin
if (psel && penable) begin
                    pready = 1'b1; 
                    
                    if (!pwrite) begin
                        prdata = memory[paddr[4:0]]; 
                    end
                    

                    if (pready) begin
                        if (!psel) 
                            next_state = IDLE;
                        else 
                            next_state = SETUP; 
                    end
                end else begin
                    next_state = IDLE; 
                end

end
default: begin
    next_state = IDLE;
end

endcase


end

always @(posedge pclk or negedge presetn) begin
    if (!presetn) begin
        state <= IDLE;
    end
    else begin
        state <= next_state;

       
    end
end

always @(*) begin
     if (state == ACCESS  && pwrite && psel && penable)
            memory[paddr[4:0]] <= pwdata;
end

endmodule

apb/tb_apb.v
`timescale 1ns/1ps

module tb_apb;

    // Inputs to DUT (Driven by Testbench -> Must be reg)
    reg         pclk;
    reg         presetn;
    reg         psel;
    reg         penable;
    reg         pwrite;
    reg  [31:0] pwdata;
    reg  [31:0] paddr;

    // Outputs from DUT (Observed by Testbench -> Must be wire)
    wire [31:0] prdata;
    wire        pready;

    // Instantiate the Device Under Test (DUT)
    apb dut (
        .pclk(pclk),
        .presetn(presetn),
        .psel(psel),
        .penable(penable),
        .pwrite(pwrite),
        .pwdata(pwdata),
        .prdata(prdata),
        .pready(pready),
        .paddr(paddr)
    );

    // Clock Generation (100ns period -> 10 MHz clock)
    always begin
        #50;
        pclk = ~pclk;
    end

    // Stimulus Generation
    initial begin
    
        pclk    = 0;
        presetn = 0;
        psel    = 0;
        penable = 0;
        pwrite  = 0;
        pwdata  = 32'd0;
        paddr   = 32'd0;

        // Reset Sequence
        #500;
        presetn = 1; // Release reset
        #200;        // Wait a couple cycles

       
        @(posedge pclk);
        #(1);
        paddr  = 32'h04;          // Address 4
        pwdata = 32'hDEADBEEF;    // Data to write
        pwrite = 1'b1;            // It's a write
        psel   = 1'b1;            // Assert PSEL -> Enters SETUP State

        @(posedge pclk);
        #(1);
        penable = 1'b1;           // Assert PENABLE -> Enters ACCESS State

        @(posedge pclk);          // Wait for clock edge where pready=1 completes transfer
       #(3);
        psel    = 1'b0;           // De-assert signals
        penable = 1'b0;
        pwrite  = 1'b0;

        #300; // IDLE gap

        @(posedge pclk);
      #(1);
        paddr  = 32'h04;          // Read from same Address 4
        pwrite = 1'b0;            // It's a read
        psel   = 1'b1;            // Enters SETUP State
        
        @(posedge pclk);
        #(1);
        penable = 1'b1;           // Enters ACCESS State

        @(posedge pclk);
        #(1);
        psel    = 1'b0;           // Complete transfer
        penable = 1'b0;

        #1000;
        $display("Simulation Finished Successfully.");
        $finish; // Added missing semicolon
    end

    // Monitor Output
    initial begin
        $monitor("Time: %0t | pclk: %b | presetn: %b | psel: %b | penable: %b | pwrite: %b | paddr: %h | pwdata: %h | prdata: %h | pready: %b", 
                 $time, pclk, presetn, psel, penable, pwrite, paddr, pwdata, prdata, pready);
    end
  initial begin
    $dumpfile("simulation_waves.vcd"); // 1. Name the output VCD file
    $dumpvars(0, tb_apb);               // 2. Dump ALL signals under tb_top
  end
endmodule

apb/simulation_waves.vcd
$date
	Thu Jul  2 08:22:40 2026
$end
$version
	Icarus Verilog
$end
$timescale
	1ps
$end
$scope module tb_apb $end
$var wire 1 ! pready $end
$var wire 32 " prdata [31:0] $end
$var reg 32 # paddr [31:0] $end
$var reg 1 $ pclk $end
$var reg 1 % penable $end
$var reg 1 & presetn $end
$var reg 1 ' psel $end
$var reg 32 ( pwdata [31:0] $end
$var reg 1 ) pwrite $end
$scope module dut $end
$var wire 32 * paddr [31:0] $end
$var wire 1 $ pclk $end
$var wire 1 % penable $end
$var wire 1 & presetn $end
$var wire 1 ' psel $end
$var wire 32 + pwdata [31:0] $end
$var wire 1 ) pwrite $end
$var reg 2 , next_state [1:0] $end
$var reg 32 - prdata [31:0] $end
$var reg 1 ! pready $end
$var reg 2 . state [1:0] $end
$var integer 32 / i [31:0] $end
$upscope $end
$upscope $end
$enddefinitions $end
#0
$dumpvars
b100000 /
b0 .
b0 -
b0 ,
b0 +
b0 *
0)
b0 (
0'
0&
0%
0$
b0 #
b0 "
0!
$end
#50000
1$
#100000
0$
#150000
1$
#200000
0$
#250000
1$
#300000
0$
#350000
1$
#400000
0$
#450000
1$
#500000
0$
1&
#550000
1$
#600000
0$
#650000
1$
#700000
0$
#750000
1$
#751000
b1 ,
1'
1)
b11011110101011011011111011101111 (
b11011110101011011011111011101111 +
b100 #
b100 *
#800000
0$
#850000
b10 ,
b1 .
1$
#851000
b10 ,
1%
#900000
0$
#950000
b1 ,
1!
b10 .
1$
#953000
0!
b0 ,
0)
0%
0'
#1000000
0$
#1050000
b0 .
1$
#1100000
0$
#1150000
1$
#1200000
0$
#1250000
1$
#1300000
0$
#1350000
1$
#1351000
b1 ,
1'
#1400000
0$
#1450000
b10 ,
b1 .
1$
#1451000
b10 ,
1%
#1500000
0$
#1550000
b1 ,
b11011110101011011011111011101111 "
b11011110101011011011111011101111 -
1!
b10 .
1$
#1551000
0!
b0 "
b0 -
b0 ,
0%
0'
#1600000
0$
#1650000
b0 .
1$
