dma/dma.v
module dma(

    input clk,
    input resetn,

    input  [3:0] addr_source,
    input  [3:0] addr_destination,
    input  [2:0] length,
    input        start,

    output       read,
    input        read_gnt,
    output [3:0] read_addr,
    input  [31:0] read_data,

    output       write,
    input        write_gnt,
    output [3:0] write_addr,
    output [31:0] write_data,

    output       done

);

reg [2:0] reg_length;
reg [3:0] reg_addr_source;
reg [3:0] reg_addr_destination;

reg [31:0] reg_read_data;

reg [1:0] state;
reg [1:0] next_state;

localparam IDLE   = 2'b00;
localparam READ   = 2'b01;
localparam WRITE  = 2'b10;
localparam FINISH = 2'b11;

// Outputs
assign read       = (state == READ);
assign write      = (state == WRITE);
assign done       = (state == FINISH);

assign read_addr  = reg_addr_source;
assign write_addr = reg_addr_destination;
assign write_data = reg_read_data;


always @(*) begin

    next_state = state;

    case(state)

        IDLE: begin
            if(start)
                next_state = READ;
        end

        READ: begin
            if(read_gnt)
                next_state = WRITE;
        end

        WRITE: begin
            if(write_gnt) begin
                if(reg_length == 1)
                    next_state = FINISH;
                else
                    next_state = READ;
            end
        end

        FINISH: begin
            next_state = IDLE;
        end

        default:
            next_state = IDLE;

    endcase
end


always @(posedge clk or negedge resetn) begin

    if(!resetn) begin

        state <= IDLE;

        reg_length <= 3'd0;
        reg_addr_source <= 4'd0;
        reg_addr_destination <= 4'd0;

        reg_read_data <= 32'd0;


    end
    else begin

        state <= next_state;


        if(state == IDLE && start) begin

            reg_length           <= length;
            reg_addr_source      <= addr_source;
            reg_addr_destination <= addr_destination;

        end

        if(state == READ && read_gnt) begin

            reg_read_data <= read_data;

        end


        if(state == WRITE && write_gnt) begin



            reg_length <= reg_length - 1;

            reg_addr_source <= reg_addr_source + 1;
            reg_addr_destination <= reg_addr_destination + 1;

        end

    end

end

endmodule

dma/tb_dma.v
`timescale 1ns / 1ps

module tb_dma;

    reg clk = 0;
    always #(5.0) clk = ~clk;

    reg rst_n = 1'b0;


    // ---- Shared DUT input signals (reg) ----
    reg [3:0] addr_destination;
    reg [3:0] addr_source;
    reg [2:0] length;
    reg [31:0] read_data;
    reg read_gnt;

    reg start;
    reg write_gnt;

    // ---- Shared DUT output signals (wire) ----

    reg [31:0] memread [0:31];
        reg [31:0] memwrite [0:31];
integer i=0;
    initial begin
        for(i=0;i<32;i++) begin
                 memread[i] = 32'hDEADBEEF;
          memwrite[i]=32'b0;
        end
    end

    




    wire done;
    wire read;
    wire [3:0] read_addr;
    wire write;
    wire [3:0] write_addr;
    wire [31:0] write_data;

    // ---- DUT: dma (u_dma) ----
    dma u_dma (
        .clk(clk),
        .resetn(rst_n),
        .addr_source(addr_source),
        .addr_destination(addr_destination),
        .length(length),
        .start(start),
        .read(read),
        .read_gnt(read_gnt),
        .read_addr(read_addr),
        .read_data(read_data),
        .write(write),
        .write_gnt(write_gnt),
        .write_addr(write_addr),
        .write_data(write_data),
        .done(done)
    );
initial begin
    start = 0;
    read_gnt = 0;
    write_gnt = 0;
    read_data = 0;
end
    initial begin
        $dumpfile("simulation");
        $dumpvars(0, tb_dma);
    end

always @(posedge clk) begin

    read_gnt <= 0;

    if(read) begin
        read_data <= memread[read_addr];
        read_gnt <= 1;
    end

end
always @(posedge clk) begin
    write_gnt <= 0;

    if(write) begin
        memwrite[write_addr] <= write_data;
        write_gnt <= 1;
    end
end

    initial begin

        #(100) rst_n = 1'b1;
        length=7;
        addr_source=0;
        addr_destination=8;

@(posedge clk);
start = 1;

@(posedge clk);
start = 0;

wait(done);

$display("DMA finished");

for(i=0;i<32;i=i+1)
    $display("%0d -> %h", i, memwrite[i]);

#20;
$finish;
    end
always @(posedge clk) begin
    #1;
    $display("T=%0t state=%0d read=%b write=%b src=%0d dst=%0d len=%0d",
             $time,
             u_dma.state,
             read,
             write,
             u_dma.reg_addr_source,
             u_dma.reg_addr_destination,
             u_dma.reg_length);
end
endmodule

dma/simulation.vcd
$date
	Thu Jul  9 16:50:11 2026
$end
$version
	Icarus Verilog
$end
$timescale
	1ps
$end
$scope module tb_dma $end
$var wire 32 ! write_data [31:0] $end
$var wire 4 " write_addr [3:0] $end
$var wire 1 # write $end
$var wire 4 $ read_addr [3:0] $end
$var wire 1 % read $end
$var wire 1 & done $end
$var reg 4 ' addr_destination [3:0] $end
$var reg 4 ( addr_source [3:0] $end
$var reg 1 ) clk $end
$var reg 3 * length [2:0] $end
$var reg 32 + read_data [31:0] $end
$var reg 1 , read_gnt $end
$var reg 1 - rst_n $end
$var reg 1 . start $end
$var reg 1 / write_gnt $end
$var integer 32 0 i [31:0] $end
$scope module u_dma $end
$var wire 4 1 addr_destination [3:0] $end
$var wire 4 2 addr_source [3:0] $end
$var wire 1 ) clk $end
$var wire 3 3 length [2:0] $end
$var wire 4 4 read_addr [3:0] $end
$var wire 32 5 read_data [31:0] $end
$var wire 1 , read_gnt $end
$var wire 1 - resetn $end
$var wire 1 . start $end
$var wire 4 6 write_addr [3:0] $end
$var wire 32 7 write_data [31:0] $end
$var wire 1 / write_gnt $end
$var wire 1 # write $end
$var wire 1 % read $end
$var wire 1 & done $end
$var reg 2 8 next_state [1:0] $end
$var reg 4 9 reg_addr_destination [3:0] $end
$var reg 4 : reg_addr_source [3:0] $end
$var reg 3 ; reg_length [2:0] $end
$var reg 32 < reg_read_data [31:0] $end
$var reg 2 = state [1:0] $end
$upscope $end
$upscope $end
$enddefinitions $end
#0
$dumpvars
b0 =
b0 <
b0 ;
b0 :
b0 9
b0 8
b0 7
b0 6
b0 5
b0 4
bx 3
bx 2
bx 1
b100000 0
0/
0.
0-
0,
b0 +
bx *
0)
bx (
bx '
0&
0%
b0 $
0#
b0 "
b0 !
$end
#5000
1)
#10000
0)
#15000
1)
#20000
0)
#25000
1)
#30000
0)
#35000
1)
#40000
0)
#45000
1)
#50000
0)
#55000
1)
#60000
0)
#65000
1)
#70000
0)
#75000
1)
#80000
0)
#85000
1)
#90000
0)
#95000
1)
#100000
0)
b1000 '
b1000 1
b0 (
b0 2
b111 *
b111 3
1-
#105000
b1000 "
b1000 6
b1000 9
b111 ;
b1 8
1.
1)
#110000
0)
#115000
1%
b1 =
b1 8
0.
1)
#120000
0)
#125000
b10 8
1,
b11011110101011011011111011101111 +
b11011110101011011011111011101111 5
1)
#130000
0)
#135000
b11011110101011011011111011101111 !
b11011110101011011011111011101111 7
b11011110101011011011111011101111 <
0%
1#
b10 =
1,
1)
#140000
0)
#145000
b1 8
0,
1/
1)
#150000
0)
#155000
b1001 "
b1001 6
b1001 9
b1 $
b1 4
b1 :
b110 ;
1%
0#
b1 =
1/
1)
#160000
0)
#165000
b10 8
1,
0/
1)
#170000
0)
#175000
0%
1#
b10 =
1,
1)
#180000
0)
#185000
b1 8
0,
1/
1)
#190000
0)
#195000
b1010 "
b1010 6
b1010 9
b10 $
b10 4
b10 :
b101 ;
1%
0#
b1 =
1/
1)
#200000
0)
#205000
b10 8
1,
0/
1)
#210000
0)
#215000
0%
1#
b10 =
1,
1)
#220000
0)
#225000
b1 8
0,
1/
1)
#230000
0)
#235000
b1011 "
b1011 6
b1011 9
b11 $
b11 4
b11 :
b100 ;
1%
0#
b1 =
1/
1)
#240000
0)
#245000
b10 8
1,
0/
1)
#250000
0)
#255000
0%
1#
b10 =
1,
1)
#260000
0)
#265000
b1 8
0,
1/
1)
#270000
0)
#275000
b1100 "
b1100 6
b1100 9
b100 $
b100 4
b100 :
b11 ;
1%
0#
b1 =
1/
1)
#280000
0)
#285000
b10 8
1,
0/
1)
#290000
0)
#295000
0%
1#
b10 =
1,
1)
#300000
0)
#305000
b1 8
0,
1/
1)
#310000
0)
#315000
b1101 "
b1101 6
b1101 9
b101 $
b101 4
b101 :
b10 ;
1%
0#
b1 =
1/
1)
#320000
0)
#325000
b10 8
1,
0/
1)
#330000
0)
#335000
0%
1#
b10 =
1,
1)
#340000
0)
#345000
b1 8
0,
1/
1)
#350000
0)
#355000
b1110 "
b1110 6
b1110 9
b110 $
b110 4
b110 :
b1 ;
1%
0#
b1 =
1/
1)
#360000
0)
#365000
b10 8
1,
0/
1)
#370000
0)
#375000
0%
1#
b10 =
1,
1)
#380000
0)
#385000
b11 8
0,
1/
1)
#390000
0)
#395000
b100000 0
b0 8
b1111 "
b1111 6
b1111 9
b111 $
b111 4
b111 :
b0 ;
0#
1&
b11 =
1/
1)
#400000
0)
#405000
0&
b0 =
0/
1)
