axi4_lite/axi.v
module axi(

    input wire aclk,
    input wire aresetn,

    input [31:0] awaddr,
    input awvalid,
    output awready,

    input [31:0] wdata,
    input [3:0] wstrb,
    input wvalid,
    output wready,

    input [31:0] araddr,
    input arvalid,
    output arready,

    output reg [31:0] rdata,
    output [1:0] rresp,
    output rvalid,
    input rready,

    output [1:0] bresp,
    output bvalid,
    input bready



);


reg [31:0] mem [0:255];


assign rresp=2'b00;


reg reg_awready;
reg reg_wready;

reg reg_arready;
reg reg_rvalid;

assign arready=reg_arready;
assign rvalid=reg_rvalid;



assign wready=reg_wready;
assign awready=reg_awready;

reg [1:0] reg_bresp;
reg reg_bvalid;

assign bresp  = reg_bresp;
assign bvalid = reg_bvalid;


always @(posedge aclk or negedge aresetn) begin
    if(!aresetn) begin
        reg_awready <= 1'b0;
        reg_wready  <= 1'b0;
        reg_bvalid  <= 1'b0;
        reg_bresp   <= 2'b00;
    end
    else begin
        // 1. Accept Write Address & Data
        if(!reg_awready && awvalid && wvalid) begin
            reg_wready      <= 1'b1;
            reg_awready     <= 1'b1;
            mem[awaddr[6:2]]<= wdata;
            
            // Trigger the write response
            reg_bvalid      <= 1'b1;
            reg_bresp       <= 2'b00; // OKAY
        end
        else begin
            reg_awready     <= 1'b0;
            reg_wready      <= 1'b0;
        end
        
        // 2. Clear Write Response when Master acknowledges it
        if(reg_bvalid && bready) begin
            reg_bvalid      <= 1'b0;
        end
    end
end

always @(posedge aclk or negedge aresetn) begin
    if (!aresetn) begin
        reg_arready <= 1'b0;
        reg_rvalid  <= 1'b0;
        rdata       <= 32'b0;
    end else begin
        // 1. Address Handshake & Data Fetch
        if (!reg_arready && arvalid) begin
            reg_arready <= 1'b1;
            reg_rvalid  <= 1'b1;
            rdata       <= mem[araddr[6:2]]; // Fetch data immediately
        end else begin
            reg_arready <= 1'b0; // Clear arready after 1 cycle
        end

        // 2. Data Handshake Completion
        if (reg_rvalid && rready) begin
            reg_rvalid  <= 1'b0; // Master took the data, clear valid
        end
    end
end




endmodule

axi4_lite/axi_tb.v
`timescale 1ns/1ps  // Switched to 1ns/1ps for a standard 100MHz clock cycle simulation length

module tb_axi;

    // Clock and Reset
    reg aclk;
    reg aresetn;

    // Write Address Channel
    reg [31:0] awaddr;
    reg awvalid;
    wire awready;

    // Write Data Channel
    reg [31:0] wdata;
    reg [3:0] wstrb;
    reg wvalid;
    wire wready;

    // Read Address Channel
    reg [31:0] araddr;
    reg arvalid;
    wire arready;

    // Read Data Channel
    wire [31:0] rdata;
    wire [1:0] rresp;
    wire rvalid;
    reg rready;

    // Write Response Channel
    wire [1:0] bresp;
    wire bvalid;
    reg bready;

    // Device Under Test (DUT)
    axi dut (
        .aclk(aclk),
        .aresetn(aresetn),
        .awaddr(awaddr),
        .awvalid(awvalid),
        .awready(awready),
        .wdata(wdata),
        .wstrb(wstrb),
        .wvalid(wvalid),
        .wready(wready),
        .araddr(araddr),
        .arvalid(arvalid),
        .arready(arready),
        .rdata(rdata),
        .rresp(rresp),
        .rvalid(rvalid),
        .rready(rready),
        .bresp(bresp),
        .bvalid(bvalid),
        .bready(bready)
    );

    // 100MHz Clock Generation (Period = 10ns)
    always begin
        #5 aclk = ~aclk;
    end 

    initial begin
        // --- 1. Initialize Inputs ---
        aclk    = 1'b0;
        aresetn = 1'b0;
        awaddr  = 32'h0;
        awvalid = 1'b0;
        wdata   = 32'h0;
        wstrb   = 4'hf;
        wvalid  = 1'b0;
        araddr  = 32'h0;
        arvalid = 1'b0;
        rready  = 1'b0;
        bready  = 1'b0;
        
        // Hold reset for 5 clock cycles
        #50;
        aresetn = 1'b1;
        #20; // Wait 2 cycles

        // --- 2. Perform a Write Transaction ---
        // Let's write the value 32'hDEADBEEF to memory address 32'h0000_0008 (Word Index 2)
        @(posedge aclk);
        awaddr  = 32'h0000_0008; 
        wdata   = 32'hDEADBEEF;
        awvalid = 1'b1;
        wvalid  = 1'b1;
        bready  = 1'b1; // Ready to receive response

        // Wait until slave accepts address and data
        @(posedge aclk);
        while (!awready || !wready) begin
            @(posedge aclk);
        end
        
        // Deassert write valids right after the handshake
        awvalid = 1'b0;
        wvalid  = 1'b0;

        // Wait for Write Response handshake (BVALID)
        while (!bvalid) begin
            @(posedge aclk);
        end
        #10; // Hold bready for one more cycle
        bready = 1'b0;

        #40; // Idle delay between transactions

        // --- 3. Perform a Read Transaction ---
        // Let's read back from the same memory address 32'h0000_0008
        @(posedge aclk);
        araddr  = 32'h0000_0008;
        arvalid = 1'b1;
        rready  = 1'b1; // Master is ready to receive data

        // Wait for Read Address handshake
        @(posedge aclk);
        while (!arready) begin
            @(posedge aclk);
        end
        arvalid = 1'b0; // Deassert address valid

        // Wait for Read Data to become valid
        while (!rvalid) begin
            @(posedge aclk);
        end
        // At this point, rdata should equal 32'hDEADBEEF!
        
        @(posedge aclk);
        rready = 1'b0; // Finish transaction

        // --- 4. End Simulation ---
        #200;
        $display("Simulation finished successfully!");
        $finish;
    end
initial begin
    $dumpfile("simulation_waves.vcd"); // 1. Name the output VCD file
    $dumpvars(0, tb_axi);               // 2. Dump ALL signals under tb_top
  end

endmodule

axi4_lite/simulation_waves.vcd
$date
	Mon Jul  6 23:16:56 2026
$end
$version
	Icarus Verilog
$end
$timescale
	1ps
$end
$scope module tb_axi $end
$var wire 2 ! rresp [1:0] $end
$var wire 1 " wready $end
$var wire 1 # rvalid $end
$var wire 32 $ rdata [31:0] $end
$var wire 1 % bvalid $end
$var wire 2 & bresp [1:0] $end
$var wire 1 ' awready $end
$var wire 1 ( arready $end
$var reg 1 ) aclk $end
$var reg 32 * araddr [31:0] $end
$var reg 1 + aresetn $end
$var reg 1 , arvalid $end
$var reg 32 - awaddr [31:0] $end
$var reg 1 . awvalid $end
$var reg 1 / bready $end
$var reg 1 0 rready $end
$var reg 32 1 wdata [31:0] $end
$var reg 4 2 wstrb [3:0] $end
$var reg 1 3 wvalid $end
$scope module dut $end
$var wire 1 ) aclk $end
$var wire 32 4 araddr [31:0] $end
$var wire 1 + aresetn $end
$var wire 1 ( arready $end
$var wire 1 , arvalid $end
$var wire 32 5 awaddr [31:0] $end
$var wire 1 ' awready $end
$var wire 1 . awvalid $end
$var wire 1 / bready $end
$var wire 2 6 bresp [1:0] $end
$var wire 1 % bvalid $end
$var wire 1 0 rready $end
$var wire 2 7 rresp [1:0] $end
$var wire 1 # rvalid $end
$var wire 32 8 wdata [31:0] $end
$var wire 1 " wready $end
$var wire 4 9 wstrb [3:0] $end
$var wire 1 3 wvalid $end
$var reg 32 : rdata [31:0] $end
$var reg 1 ; reg_arready $end
$var reg 1 < reg_awready $end
$var reg 2 = reg_bresp [1:0] $end
$var reg 1 > reg_bvalid $end
$var reg 1 ? reg_rvalid $end
$var reg 1 @ reg_wready $end
$upscope $end
$upscope $end
$enddefinitions $end
#0
$dumpvars
0@
0?
0>
b0 =
0<
0;
b0 :
b1111 9
b0 8
b0 7
b0 6
b0 5
b0 4
03
b1111 2
b0 1
00
0/
0.
b0 -
0,
0+
b0 *
0)
0(
0'
b0 &
0%
b0 $
0#
0"
b0 !
$end
#5000
1)
#10000
0)
#15000
1)
#20000
0)
#25000
1)
#30000
0)
#35000
1)
#40000
0)
#45000
1)
#50000
0)
1+
#55000
1)
#60000
0)
#65000
1)
#70000
0)
#75000
1%
1>
1'
1<
1"
1@
1/
13
1.
b11011110101011011011111011101111 1
b11011110101011011011111011101111 8
b1000 -
b1000 5
1)
#80000
0)
#85000
0%
0>
0"
0@
0'
0<
03
0.
1)
#90000
0)
#95000
1)
0/
#100000
0)
#105000
1)
#110000
0)
#115000
1)
#120000
0)
#125000
1)
#130000
0)
#135000
b11011110101011011011111011101111 $
b11011110101011011011111011101111 :
1#
1?
1(
1;
10
1,
b1000 *
b1000 4
1)
#140000
0)
#145000
0#
0?
0(
0;
0,
1)
#150000
0)
#155000
00
1)
