ahb/ahb.v
module ahb(

input hclk,
input hresetn,

input hsel,
input [31:0] haddr,
input [1:0] htrans,
input [2:0] hsize,
input [31:0] hwdata,
input hready,
input hwrite,

output reg[31:0] hrdata,
output reg hreadyout,
output reg hresp

);

reg [31:0] mem[0:255];

//these registers are because of pipelineing
reg [31:0] addr_reg;
reg        write_reg;
reg [2:0]  size_reg;
reg        valid_reg;


always @(posedge hclk or negedge hresetn) begin
    
    if(!hresetn) begin
        
        //reset
        hrdata<=32'b0;
        hreadyout<=1;
        hresp<=0;

        addr_reg<=32'b0;
        write_reg<=0;
        size_reg<=3'b0;
        valid_reg<=0;

    end
    else begin
      if(valid_reg) begin
            
            if(write_reg) begin //write
              mem[addr_reg[9:2]]<=hwdata;


            end
            else begin //read
              
                hrdata<=mem[addr_reg[9:2]];

            end


        end




  
    if(hsel&&hready&&htrans[1]) begin
      addr_reg<=haddr;
        write_reg<=hwrite;
        size_reg<=hsize;
        valid_reg<=1'b1;
        
        
    end
    else begin
      valid_reg<=1'b0;
        //ignore

    end 
hreadyout <= 1'b1;
        hresp     <= 1'b0;
end
end


endmodule

ahb/ahb_tb.v
`timescale 1ps/1ps
module ahb_tb;


ahb dut(

.hclk(hclk),
.hresetn( hresetn),

.hsel( hsel),
.haddr(haddr),
.htrans(htrans),
.hsize(hsize),
.hwdata(hwdata),
.hready(hready),
.hwrite(hwrite),

.hrdata(hrdata),
.hreadyout(hreadyout),
.hresp(hresp)

);
reg [31:0] read_data;
task write;
input [31:0] addr;
input [31:0] data;
begin

    // Address phase
    @(negedge hclk);
    hsel   = 1;
    haddr  = addr;
    hwrite = 1;
    htrans = 2'b10;
    hsize  = 3'b010;

    // Data phase
    @(posedge hclk);
    hwdata = data;

    // Finish
    @(posedge hclk);
    hsel   = 0;
    htrans = 2'b00;
hwrite = 0;
end
endtask

task read;
    input [31:0] addr;
    output [31:0] data_output;
    begin

@(posedge hclk);
    hsel   = 1;
    haddr  = addr;
    hwrite = 0;
    htrans = 2'b10;
    hsize  = 3'b010;

@(posedge hclk);
#1
data_output = hrdata;

    // Finish
    @(posedge hclk);
    hsel   = 0;
    htrans = 2'b00;
        
    end
endtask
reg hclk;
reg hresetn;

reg hsel;
reg [31:0] haddr;
reg [1:0] htrans;
reg [2:0] hsize;
reg [31:0] hwdata;
reg hready;
reg hwrite;

wire [31:0] hrdata;
wire hreadyout;
wire  hresp;

always begin
    #50;
    hclk=~hclk;
end
initial begin

    hclk=1'b0;


 hsel=1'b0;
haddr=32'b0;
 htrans=2'b0;
hsize=3'b0;
hwdata=32'b0;
hready=1'b1;
 hwrite=1'b0;
    hresetn=1'b0;
    #500;
    hresetn=1'b1;

       write(
32'd4,
32'hDEADBEEF

       );


        read(
32'd4,
read_data        );

    #100;

$display("Read Data = %h",read_data);

   
$finish;
end

initial begin
  $monitor(
"t=%0t HADDR=%h HWRITE=%b HWDATA=%h HRDATA=%h READ_DATA=%h",
$time,haddr,hwrite,hwdata,hrdata,read_data
);
end 
initial begin
    $dumpfile("simulation_waves.vcd"); // 1. Name the output VCD file
    $dumpvars(0, ahb_tb);               // 2. Dump ALL signals under tb_top
  end


endmodule

ahb/simulation_waves.vcd
$date
	Fri Jul  3 08:07:58 2026
$end
$version
	Icarus Verilog
$end
$timescale
	1ps
$end
$scope module ahb_tb $end
$var wire 1 ! hresp $end
$var wire 1 " hreadyout $end
$var wire 32 # hrdata [31:0] $end
$var reg 32 $ haddr [31:0] $end
$var reg 1 % hclk $end
$var reg 1 & hready $end
$var reg 1 ' hresetn $end
$var reg 1 ( hsel $end
$var reg 3 ) hsize [2:0] $end
$var reg 2 * htrans [1:0] $end
$var reg 32 + hwdata [31:0] $end
$var reg 1 , hwrite $end
$var reg 32 - read_data [31:0] $end
$scope module dut $end
$var wire 32 . haddr [31:0] $end
$var wire 1 % hclk $end
$var wire 1 & hready $end
$var wire 1 ' hresetn $end
$var wire 1 ( hsel $end
$var wire 3 / hsize [2:0] $end
$var wire 2 0 htrans [1:0] $end
$var wire 32 1 hwdata [31:0] $end
$var wire 1 , hwrite $end
$var reg 32 2 addr_reg [31:0] $end
$var reg 32 3 hrdata [31:0] $end
$var reg 1 " hreadyout $end
$var reg 1 ! hresp $end
$var reg 3 4 size_reg [2:0] $end
$var reg 1 5 valid_reg $end
$var reg 1 6 write_reg $end
$upscope $end
$scope task read $end
$var reg 32 7 addr [31:0] $end
$var reg 32 8 data_output [31:0] $end
$upscope $end
$scope task write $end
$var reg 32 9 addr [31:0] $end
$var reg 32 : data [31:0] $end
$upscope $end
$upscope $end
$enddefinitions $end
#0
$dumpvars
bx :
bx 9
bx 8
bx 7
06
05
b0 4
b0 3
b0 2
b0 1
b0 0
b0 /
b0 .
bx -
0,
b0 +
b0 *
b0 )
0(
0'
1&
0%
b0 $
b0 #
1"
0!
$end
#50
1%
#100
0%
#150
1%
#200
0%
#250
1%
#300
0%
#350
1%
#400
0%
#450
1%
#500
b10 )
b10 /
b10 *
b10 0
1,
b100 $
b100 .
1(
0%
b11011110101011011011111011101111 :
b100 9
1'
#550
15
b10 4
16
b100 2
b11011110101011011011111011101111 +
b11011110101011011011111011101111 1
1%
#600
0%
#650
05
b100 7
0,
b0 *
b0 0
0(
1%
#700
0%
#750
15
06
b10 *
b10 0
1(
1%
#800
0%
#850
b11011110101011011011111011101111 #
b11011110101011011011111011101111 3
1%
#851
b11011110101011011011111011101111 8
#900
0%
#950
05
b11011110101011011011111011101111 -
b0 *
b0 0
0(
1%
