spi/spi_slave/spi.v
module spi(

input clk,
input mosi,
output miso,
input cs


);
reg [7:0] miso_data=8'b10000001;
reg [7:0] mosi_data;

reg [3:0] index=4'd7;


assign miso=cs?1'b0:miso_data[index];
always @(posedge clk) begin
    
    if(cs) begin
      //pass
        index<=4'd7;

    end
    else begin

      mosi_data[index]<=mosi;
if (index == 3'd0) begin
            index <= 3'd7; // Wrap around after the LSB is processed
        end 
        else begin
            index <= index - 1'b1; // Decrement index
        end
    end


end 


endmodule

spi/spi_slave/tb_spi.v
`timescale 1ns / 1ps

module tb_spi;

    reg clk = 0;
    always #(5.0) clk = ~clk; // 100MHz clock

    // ---- Shared DUT input signals ----
    reg done = 1'b0;
    reg cs;
    reg mosi = 1'b0;          // Initialized to prevent X propagation
    reg [7:0] miso_data;

    // ---- Shared DUT output signals ----
    wire miso;

    // ---- DUT: spi ----
    spi dut (
        .clk(clk),
        .mosi(mosi),
        .miso(miso),
        .cs(cs)
    );

    initial begin
        $dumpfile("tb_spi.vcd");
        $dumpvars(0, tb_spi);
    end

    initial begin
        cs = 1'b1;            // Start with CS high (idle)
        #100;
        cs = 1'b0;            // Activate SPI transmission
        
        $monitor("time=%t | mosi=%d | miso=%b | cs=%d | index=%d |tb_index=%d|  captured_miso=%b", 
                 $time, mosi, miso, cs, dut.index,tb_index, miso_data);
    end

    // Finish simulation gracefully when done goes high
    always @(posedge done) begin
        #10; 
        $display("Simulation finished successfully. Captured MISO: %h", miso_data);
        $finish;
    end

    // Testbench data capture logic
    reg [3:0] tb_index = 4'd7; // Start at MSB (7)
    
always @(negedge clk) begin
        if (!cs) begin
            miso_data[tb_index] <= miso; // Safely sample stable MISO line
            
            if (tb_index == 3'd0) begin
                done <= 1'b1;            // Signal completion after LSB (bit 0) is sampled
            end else begin
                tb_index <= tb_index - 1'b1;
            end
        end
        else begin
            tb_index <= 3'd7;            // Reset index if CS pulled high
        end
    end
endmodule

spi/spi_slave/tb_spi.vcd
$date
	Mon Jul 13 01:57:54 2026
$end
$version
	Icarus Verilog
$end
$timescale
	1ps
$end
$scope module tb_spi $end
$var wire 1 ! miso $end
$var reg 1 " clk $end
$var reg 1 # cs $end
$var reg 1 $ done $end
$var reg 8 % miso_data [7:0] $end
$var reg 1 & mosi $end
$var reg 4 ' tb_index [3:0] $end
$scope module dut $end
$var wire 1 " clk $end
$var wire 1 # cs $end
$var wire 1 & mosi $end
$var wire 1 ! miso $end
$var reg 4 ( index [3:0] $end
$var reg 8 ) miso_data [7:0] $end
$var reg 8 * mosi_data [7:0] $end
$upscope $end
$upscope $end
$enddefinitions $end
#0
$dumpvars
bx *
b10000001 )
b111 (
b111 '
0&
bx %
0$
1#
0"
0!
$end
#5000
1"
#10000
0"
#15000
1"
#20000
0"
#25000
1"
#30000
0"
#35000
1"
#40000
0"
#45000
1"
#50000
0"
#55000
1"
#60000
0"
#65000
1"
#70000
0"
#75000
1"
#80000
0"
#85000
1"
#90000
0"
#95000
1"
#100000
b110 '
b1xxxxxxx %
1!
0"
0#
#105000
0!
b110 (
b0xxxxxxx *
1"
#110000
b101 '
b10xxxxxx %
0"
#115000
b101 (
b0xxxxxx *
1"
#120000
b100 '
b100xxxxx %
0"
#125000
b100 (
b0xxxxx *
1"
#130000
b11 '
b1000xxxx %
0"
#135000
b11 (
b0xxxx *
1"
#140000
b10 '
b10000xxx %
0"
#145000
b10 (
b0xxx *
1"
#150000
b1 '
b100000xx %
0"
#155000
b1 (
b0xx *
1"
#160000
b0 '
b1000000x %
0"
#165000
1!
b0 (
b0x *
1"
#170000
1$
b10000001 %
0"
#175000
b111 (
b0 *
1"
